odoo9_addon_mrp_production_putaway_strategy-9.0.1.0.0-py2.7-nspkg.pth
odoo9_addon_mrp_production_putaway_strategy-9.0.1.0.0.dist-info/DESCRIPTION.rst
odoo9_addon_mrp_production_putaway_strategy-9.0.1.0.0.dist-info/METADATA
odoo9_addon_mrp_production_putaway_strategy-9.0.1.0.0.dist-info/RECORD
odoo9_addon_mrp_production_putaway_strategy-9.0.1.0.0.dist-info/WHEEL
odoo9_addon_mrp_production_putaway_strategy-9.0.1.0.0.dist-info/metadata.json
odoo9_addon_mrp_production_putaway_strategy-9.0.1.0.0.dist-info/namespace_packages.txt
odoo9_addon_mrp_production_putaway_strategy-9.0.1.0.0.dist-info/top_level.txt
odoo_addons/mrp_production_putaway_strategy/README.rst
odoo_addons/mrp_production_putaway_strategy/__init__.py
odoo_addons/mrp_production_putaway_strategy/__openerp__.py
odoo_addons/mrp_production_putaway_strategy/models/__init__.py
odoo_addons/mrp_production_putaway_strategy/models/mrp_production.py
odoo_addons/mrp_production_putaway_strategy/static/description/icon.png
odoo_addons/mrp_production_putaway_strategy/tests/__init__.py
odoo_addons/mrp_production_putaway_strategy/tests/test_mrp_production.py
